odoo/addons/account_asset_transfer_operating_unit/README.rst
odoo/addons/account_asset_transfer_operating_unit/__init__.py
odoo/addons/account_asset_transfer_operating_unit/__manifest__.py
odoo/addons/account_asset_transfer_operating_unit/i18n/account_asset_transfer_operating_unit.pot
odoo/addons/account_asset_transfer_operating_unit/readme/CONTRIBUTORS.rst
odoo/addons/account_asset_transfer_operating_unit/readme/DESCRIPTION.rst
odoo/addons/account_asset_transfer_operating_unit/static/description/icon.png
odoo/addons/account_asset_transfer_operating_unit/static/description/index.html
odoo/addons/account_asset_transfer_operating_unit/tests/__init__.py
odoo/addons/account_asset_transfer_operating_unit/tests/test_asset_transfer_operating_unit.py
odoo/addons/account_asset_transfer_operating_unit/wizard/__init__.py
odoo/addons/account_asset_transfer_operating_unit/wizard/account_asset_transfer.py
odoo/addons/account_asset_transfer_operating_unit/wizard/account_asset_transfer.xml
odoo_addon_account_asset_transfer_operating_unit-15.0.1.0.0.2.dist-info/METADATA
odoo_addon_account_asset_transfer_operating_unit-15.0.1.0.0.2.dist-info/WHEEL
odoo_addon_account_asset_transfer_operating_unit-15.0.1.0.0.2.dist-info/top_level.txt
odoo_addon_account_asset_transfer_operating_unit-15.0.1.0.0.2.dist-info/RECORD
